{"cameraMode":{"drawMode":0,"name":"Shaded","section":"Shading Mode"},"sceneLighting":true,"audioPlay":false,"sceneViewState":{"showFog":true,"showMaterialUpdate":false,"showSkybox":true,"showFlares":true,"showImageEffects":true,"showParticleSystems":true},"in2DMode":false,"pivot":{"x":1.5780835151672364,"y":4.451562404632568,"z":-8.20809268951416},"rotation":{"x":0.16869056224822999,"y":-0.0011871547903865576,"z":0.0002036691876128316,"w":0.9856742024421692},"size":6.364743709564209,"orthographic":false}